aef/__init__.py
aef/__main__.py
aef/blutooth_control.py
aef/commands.py
aef/constants.py
aef/default_files.py
aef/effects_handler.py
aef/global_commands.py
aef/jack_handler.py
aef/jack_node.py
aef/log.py
aef/msg_list.py
aef/pd_handler.py
aef/pd_parser.py
aef/pd_routing_handler.py
aef/preset_handler.py
aef/recorder.py
aef/settings.py
aef/shell.py
aef/files/__init__.py
aef/files/default_pd.py
aef/files/default_registry.py
aef/files/global_pd.py
aef/files/top_pd.py
aef-0.1.2.dist-info/COPYING
aef-0.1.2.dist-info/METADATA
aef-0.1.2.dist-info/WHEEL
aef-0.1.2.dist-info/top_level.txt
aef-0.1.2.dist-info/RECORD
