Metadata-Version: 2.1
Name: aef
Version: 0.1.2
Summary: A tool to setup arbitrary guitar effects pedals
Home-page: https://github.com/c3n3/aef
Author: Caden Churchman
Author-email: ccaden21@gmail.com
Project-URL: Bug Tracker, https://github.com/c3n3/aef/issues
Classifier: Programming Language :: Python :: 3
Classifier: License :: OSI Approved :: GNU General Public License v3 (GPLv3)
Classifier: Operating System :: POSIX :: Linux
Requires-Python: >=3.8
License-File: COPYING
